[
   {
      "facts":[
         {
            "day":"10",
            "month":"1",
            "year":"49 BC ",
            "text":"Julius Caesar crosses the Rubicon, signaling the start of civil war."
         },
         {
            "day":"10",
            "month":"1",
            "year":"69 ",
            "text":"Roman emperor Galba adopts Marcus Piso Licinianus as Caesar"
         },
         {
            "day":"10",
            "month":"1",
            "year":"236 ",
            "text":"St Fabian begins his reign as Catholic Pope"
         },
         {
            "day":"10",
            "month":"1",
            "year":"1072 ",
            "text":"Robert Guiscard conquers Palermo"
         },
         {
            "day":"10",
            "month":"1",
            "year":"1356 ",
            "text":"German emperor Charles I delegates Golden Degree"
         },
         {
            "day":"10",
            "month":"1",
            "year":"1429 ",
            "text":"Order of Golden Fleece established in Austria-Hungary & Spain"
         },
         {
            "day":"10",
            "month":"1",
            "year":"1430 ",
            "text":"Order of the Guilder forms"
         },
         {
            "day":"10",
            "month":"1",
            "year":"1475 ",
            "text":"Stephen III of Moldavia defeats the Ottoman Empire at the Battle of Vaslui."
         },
         {
            "day":"10",
            "month":"1",
            "year":"1514 ",
            "text":"Complutensian New Testament in Hebrew, Aramaic, Greek & Latin finished"
         },
         {
            "day":"10",
            "month":"1",
            "year":"1550 ",
            "text":"1st sitting of \"Vurige Chamber\" in Paris"
         },
         {
            "day":"10",
            "month":"1",
            "year":"1642 ",
            "text":"King Charles I & family flee London for Oxford"
         },
         {
            "day":"10",
            "month":"1",
            "year":"1663 ",
            "text":"King Charles II affirms charter of Royal African Company"
         },
         {
            "day":"10",
            "month":"1",
            "year":"1731 ",
            "text":"Charles Farnese becomes duke of Parma/Piacenza"
         },
         {
            "day":"10",
            "month":"1",
            "year":"1776 ",
            "text":"\"Common Sense\" Pamphlet by Thomas Paine, published advocating American independence"
         },
         {
            "day":"10",
            "month":"1",
            "year":"1799 ",
            "text":"Friedrich von Schiller's \"Die Piccolomini,\" premieres in Weimar"
         }
      ]
   }
]
